odoo/addons/shopfloor_rest_log/README.rst
odoo/addons/shopfloor_rest_log/__init__.py
odoo/addons/shopfloor_rest_log/__manifest__.py
odoo/addons/shopfloor_rest_log/hooks.py
odoo/addons/shopfloor_rest_log/i18n/es_AR.po
odoo/addons/shopfloor_rest_log/i18n/shopfloor_rest_log.pot
odoo/addons/shopfloor_rest_log/migrations/13.0.1.1.0/pre-migration.py
odoo/addons/shopfloor_rest_log/readme/CONTRIBUTORS.rst
odoo/addons/shopfloor_rest_log/readme/DESCRIPTION.rst
odoo/addons/shopfloor_rest_log/readme/HISTORY.rst
odoo/addons/shopfloor_rest_log/readme/USAGE.rst
odoo/addons/shopfloor_rest_log/security/groups.xml
odoo/addons/shopfloor_rest_log/static/description/icon.png
odoo/addons/shopfloor_rest_log/static/description/index.html
odoo/addons/shopfloor_rest_log/views/menus.xml
odoo13_addon_shopfloor_rest_log-13.0.1.2.0.dist-info/METADATA
odoo13_addon_shopfloor_rest_log-13.0.1.2.0.dist-info/WHEEL
odoo13_addon_shopfloor_rest_log-13.0.1.2.0.dist-info/top_level.txt
odoo13_addon_shopfloor_rest_log-13.0.1.2.0.dist-info/RECORD
