Metadata-Version: 2.1
Name: odoo13-addon-shopfloor-rest-log
Version: 13.0.1.2.0
Summary: Integrate rest_log into Shopfloor app
Home-page: https://github.com/OCA/wms
Author: ACSONE, Odoo Community Association (OCA)
Author-email: support@odoo-community.org
License: LGPL-3
Platform: UNKNOWN
Classifier: Programming Language :: Python
Classifier: Framework :: Odoo
Classifier: License :: OSI Approved :: GNU Lesser General Public License v3 (LGPLv3)
Classifier: Development Status :: 4 - Beta
Requires-Python: >=3.5
Requires-Dist: odoo13-addon-rest-log
Requires-Dist: odoo13-addon-shopfloor-base
Requires-Dist: odoo (<13.1dev,>=13.0a)
